{"Org_ID":{"mark":"主键","intro":"","relation":""},"Org_Lang":{"mark":"","intro":"","relation":""},"Org_Name":{"mark":"名称","intro":"机构的名称","relation":""},"Org_PlatformName":{"mark":"平台名称","intro":"网校的名称，即当前机构在平台中显示的平台名称","relation":""},"Org_Keywords":{"mark":"","intro":"","relation":""},"Org_Description":{"mark":"","intro":"","relation":""},"Org_EnName":{"mark":"","intro":"","relation":""},"Org_AbbrName":{"mark":"","intro":"","relation":""},"Org_AbbrEnName":{"mark":"","intro":"","relation":""},"Org_Address":{"mark":"","intro":"","relation":""},"Org_Phone":{"mark":"","intro":"","relation":""},"Org_Fax":{"mark":"","intro":"","relation":""},"Org_Zip":{"mark":"","intro":"","relation":""},"Org_WebSite":{"mark":"","intro":"","relation":""},"Org_TwoDomain":{"mark":"","intro":"","relation":""},"Org_Email":{"mark":"","intro":"","relation":""},"Org_Weixin":{"mark":"","intro":"","relation":""},"Org_Intro":{"mark":"","intro":"","relation":""},"Org_CoBank":{"mark":"","intro":"","relation":""},"Org_BankAcc":{"mark":"","intro":"","relation":""},"Org_Owner":{"mark":"","intro":"","relation":""},"Org_License":{"mark":"","intro":"","relation":""},"Org_LicensePic":{"mark":"","intro":"","relation":""},"Org_Longitude":{"mark":"","intro":"","relation":""},"Org_Latitude":{"mark":"","intro":"","relation":""},"Org_Province":{"mark":"","intro":"","relation":""},"Org_City":{"mark":"","intro":"","relation":""},"Org_District":{"mark":"","intro":"","relation":""},"Org_Street":{"mark":"","intro":"","relation":""},"Org_Logo":{"mark":"","intro":"","relation":""},"Org_QrCodeUrl":{"mark":"","intro":"","relation":""},"Org_RegTime":{"mark":"","intro":"","relation":""},"Org_IsRoot":{"mark":"","intro":"","relation":""},"Org_IsUse":{"mark":"","intro":"","relation":""},"Org_IsPass":{"mark":"","intro":"","relation":""},"Org_IsDefault":{"mark":"","intro":"","relation":""},"Olv_ID":{"mark":"","intro":"","relation":""},"Olv_Name":{"mark":"","intro":"","relation":""},"Org_Linkman":{"mark":"","intro":"","relation":""},"Org_LinkmanPhone":{"mark":"","intro":"","relation":""},"Org_LinkmanQQ":{"mark":"","intro":"","relation":""},"Org_Template":{"mark":"","intro":"","relation":""},"Org_Extracode":{"mark":"","intro":"","relation":""},"Org_Config":{"mark":"","intro":"","relation":""},"Org_TemplateMobi":{"mark":"","intro":"","relation":""},"Org_IsShow":{"mark":"","intro":"","relation":""},"Org_ICP":{"mark":"ICP备案号","intro":"","relation":""},"Org_QrCode":{"mark":"","intro":"","relation":""},"Org_GonganBeian":{"mark":"","intro":"","relation":""}}